mo_kwargs/__init__.py
mo_kwargs-7.685.25166.dist-info/licenses/LICENSE
mo_kwargs-7.685.25166.dist-info/METADATA
mo_kwargs-7.685.25166.dist-info/WHEEL
mo_kwargs-7.685.25166.dist-info/top_level.txt
mo_kwargs-7.685.25166.dist-info/RECORD
